semantic_model_generator/__init__.py
semantic_model_generator/clickzetta_utils/clickzetta_connector.py
semantic_model_generator/clickzetta_utils/env_vars.py
semantic_model_generator/clickzetta_utils/utils.py
semantic_model_generator/data_processing/__init__.py
semantic_model_generator/data_processing/cte_utils.py
semantic_model_generator/data_processing/cte_utils_test.py
semantic_model_generator/data_processing/data_types.py
semantic_model_generator/data_processing/proto_utils.py
semantic_model_generator/generate_model.py
semantic_model_generator/llm/__init__.py
semantic_model_generator/llm/dashscope_client.py
semantic_model_generator/llm/enrichment.py
semantic_model_generator/llm/progress_tracker.py
semantic_model_generator/output_models/.keep
semantic_model_generator/protos/semantic_model.proto
semantic_model_generator/protos/semantic_model_pb2.py
semantic_model_generator/protos/semantic_model_pb2.pyi
semantic_model_generator/relationships/__init__.py
semantic_model_generator/relationships/discovery.py
semantic_model_generator/relationships/tests/__init__.py
semantic_model_generator/relationships/tests/test_reference_schemas.py
semantic_model_generator/tests/clickzetta_connector_test.py
semantic_model_generator/tests/cte_utils_test.py
semantic_model_generator/tests/generate_model_classification_test.py
semantic_model_generator/tests/llm_enrichment_test.py
semantic_model_generator/tests/relationship_discovery_test.py
semantic_model_generator/tests/relationships_filters_test.py
semantic_model_generator/tests/samples/validate_yamls.py
semantic_model_generator/tests/utils_test.py
semantic_model_generator/tests/validate_model_test.py
semantic_model_generator/tests/yaml_to_semantic_model_test.py
semantic_model_generator/validate/context_length.py
semantic_model_generator/validate/keywords.py
semantic_model_generator/validate/schema.py
semantic_model_generator/validate_model.py
clickzetta_semantic_model_generator-1.0.54.dist-info/LICENSE
clickzetta_semantic_model_generator-1.0.54.dist-info/METADATA
clickzetta_semantic_model_generator-1.0.54.dist-info/WHEEL
clickzetta_semantic_model_generator-1.0.54.dist-info/RECORD
