Metadata-Version: 2.3
Name: clickzetta-semantic-model-generator
Version: 1.0.54
Summary: Curate a Semantic Model for ClickZetta Lakehouse
License: Apache Software License; BSD License
Author: qililiang
Author-email: qililiang@clickzetta.com
Requires-Python: >=3.9, !=2.7.*, !=3.0.*, !=3.1.*, !=3.2.*, !=3.3.*, !=3.4.*, !=3.5.*, !=3.6.*, !=3.7.*, !=3.8.*, !=3.12.*, !=3.13.*
Classifier: License :: Other/Proprietary License
Classifier: Programming Language :: Python :: 3
Classifier: Programming Language :: Python :: 3.9
Classifier: Programming Language :: Python :: 3.10
Classifier: Programming Language :: Python :: 3.11
Provides-Extra: looker
Requires-Dist: PyYAML (>=6.0.1,<7.0.0)
Requires-Dist: clickzetta-connector-python (>=0.8.92)
Requires-Dist: clickzetta-zettapark-python (>=0.1.3)
Requires-Dist: dashscope (>=1.22.2,<2.0.0)
Requires-Dist: loguru (>=0.7.2,<0.8.0)
Requires-Dist: looker-sdk (>=24.14.0,<25.0.0) ; extra == "looker"
Requires-Dist: numpy (>=1.26.4,<3.0.0)
Requires-Dist: pandas (>=2.0.1,<3.0.0)
Requires-Dist: protobuf (==5.26.1)
Requires-Dist: pyarrow (==14.0.2)
Requires-Dist: pydantic (>=2.8.2,<3.0.0)
Requires-Dist: python-dotenv (>=1.0.1,<2.0.0)
Requires-Dist: requests (>=2.32.3,<3.0.0)
Requires-Dist: ruamel.yaml (==0.17.21)
Requires-Dist: sqlglot (==25.10.0)
Requires-Dist: streamlit (==1.36.0)
Requires-Dist: streamlit-extras (==0.4.0)
Requires-Dist: strictyaml (>=1.7.3,<2.0.0)
Requires-Dist: tqdm (>=4.66.5,<5.0.0)
Requires-Dist: urllib3 (>=1.26.19,<3.0.0)
